jupyter_server/__init__.py
jupyter_server/__main__.py
jupyter_server/_sysinfo.py
jupyter_server/_tz.py
jupyter_server/_version.py
jupyter_server/config_manager.py
jupyter_server/log.py
jupyter_server/py.typed
jupyter_server/pytest_plugin.py
jupyter_server/serverapp.py
jupyter_server/traittypes.py
jupyter_server/transutils.py
jupyter_server/utils.py
jupyter_server/auth/__init__.py
jupyter_server/auth/__main__.py
jupyter_server/auth/authorizer.py
jupyter_server/auth/decorator.py
jupyter_server/auth/identity.py
jupyter_server/auth/login.py
jupyter_server/auth/logout.py
jupyter_server/auth/security.py
jupyter_server/auth/utils.py
jupyter_server/base/__init__.py
jupyter_server/base/call_context.py
jupyter_server/base/handlers.py
jupyter_server/base/websocket.py
jupyter_server/base/zmqhandlers.py
jupyter_server/event_schemas/contents_service/v1.yaml
jupyter_server/event_schemas/gateway_client/v1.yaml
jupyter_server/event_schemas/kernel_actions/v1.yaml
jupyter_server/extension/__init__.py
jupyter_server/extension/application.py
jupyter_server/extension/config.py
jupyter_server/extension/handler.py
jupyter_server/extension/manager.py
jupyter_server/extension/serverextension.py
jupyter_server/extension/utils.py
jupyter_server/files/__init__.py
jupyter_server/files/handlers.py
jupyter_server/gateway/__init__.py
jupyter_server/gateway/connections.py
jupyter_server/gateway/gateway_client.py
jupyter_server/gateway/handlers.py
jupyter_server/gateway/managers.py
jupyter_server/i18n/README.md
jupyter_server/i18n/__init__.py
jupyter_server/i18n/babel_nbui.cfg
jupyter_server/i18n/babel_notebook.cfg
jupyter_server/i18n/nbjs.json
jupyter_server/i18n/nbui.pot
jupyter_server/i18n/notebook.pot
jupyter_server/i18n/zh_CN/LC_MESSAGES/nbui.po
jupyter_server/i18n/zh_CN/LC_MESSAGES/notebook.po
jupyter_server/kernelspecs/__init__.py
jupyter_server/kernelspecs/handlers.py
jupyter_server/nbconvert/__init__.py
jupyter_server/nbconvert/handlers.py
jupyter_server/prometheus/__init__.py
jupyter_server-2.12.0.dist-info/METADATA
jupyter_server-2.12.0.dist-info/WHEEL
jupyter_server-2.12.0.dist-info/entry_points.txt
jupyter_server-2.12.0.dist-info/licenses/LICENSE
jupyter_server-2.12.0.dist-info/RECORD
