Metadata-Version: 2.1
Name: jupyter_server
Version: 2.12.0
Summary: The backend—i.e. core services, APIs, and REST endpoints—to Jupyter web applications.
Project-URL: Homepage, https://jupyter-server.readthedocs.io
Project-URL: Documentation, https://jupyter-server.readthedocs.io
Project-URL: Funding, https://numfocus.org/donate
Project-URL: Source, https://github.com/jupyter-server/jupyter_server
Project-URL: Tracker, https://github.com/jupyter-server/jupyter_server/issues
Author-email: Jupyter Development Team <jupyter@googlegroups.com>
License: BSD 3-Clause License
License-File: LICENSE
Keywords: ipython,jupyter
Classifier: Development Status :: 5 - Production/Stable
Classifier: Framework :: Jupyter
Classifier: Intended Audience :: Developers
Classifier: Intended Audience :: Science/Research
Classifier: Intended Audience :: System Administrators
Classifier: License :: OSI Approved :: BSD License
Classifier: Programming Language :: Python
Classifier: Programming Language :: Python :: 3
Classifier: Programming Language :: Python :: 3 :: Only
Requires-Python: >=3.8
Requires-Dist: anyio>=3.1.0
Requires-Dist: argon2-cffi
Requires-Dist: jinja2
Requires-Dist: jupyter-client>=7.4.4
Requires-Dist: jupyter-core!=5.0.*,>=4.12
Requires-Dist: jupyter-events>=0.9.0
Requires-Dist: jupyter-server-terminals
Requires-Dist: nbconvert>=6.4.4
Requires-Dist: nbformat>=5.3.0
Requires-Dist: overrides
Requires-Dist: packaging
Requires-Dist: prometheus-client
Requires-Dist: pywinpty; os_name == 'nt'
Requires-Dist: pyzmq>=24
Requires-Dist: send2trash>=1.8.2
Requires-Dist: terminado>=0.8.3
Requires-Dist: tornado>=6.2.0
Requires-Dist: traitlets>=5.6.0
Requires-Dist: websocket-client
Provides-Extra: docs
Requires-Dist: ipykernel; extra == 'docs'
Requires-Dist: jinja2; extra == 'docs'
Requires-Dist: jupyter-client; extra == 'docs'
Requires-Dist: jupyter-server; extra == 'docs'
Requires-Dist: myst-parser; extra == 'docs'
Requires-Dist: nbformat; extra == 'docs'
Requires-Dist: prometheus-client; extra == 'docs'
Requires-Dist: pydata-sphinx-theme; extra == 'docs'
Requires-Dist: send2trash; extra == 'docs'
Requires-Dist: sphinx-autodoc-typehints; extra == 'docs'
Requires-Dist: sphinxcontrib-github-alt; extra == 'docs'
Requires-Dist: sphinxcontrib-openapi>=0.8.0; extra == 'docs'
Requires-Dist: sphinxcontrib-spelling; extra == 'docs'
Requires-Dist: sphinxemoji; extra == 'docs'
Requires-Dist: tornado; extra == 'docs'
Requires-Dist: typing-extensions; extra == 'docs'
Provides-Extra: test
Requires-Dist: flaky; extra == 'test'
Requires-Dist: ipykernel; extra == 'test'
Requires-Dist: pre-commit; extra == 'test'
Requires-Dist: pytest-console-scripts; extra == 'test'
Requires-Dist: pytest-jupyter[server]>=0.4; extra == 'test'
Requires-Dist: pytest-timeout; extra == 'test'
Requires-Dist: pytest>=7.0; extra == 'test'
Requires-Dist: requests; extra == 'test'
